tj_text/__init__.py
tj_text/typograph/__init__.py
tj_text/typograph/chars.py
tj_text/typograph/constants.py
tj_text/typograph/core.py
tj_text/typograph/mixins.py
tj_text/typograph/processors.py
tj_text/typograph/utils.py
tj_text-0.10.0.dist-info/WHEEL
tj_text-0.10.0.dist-info/METADATA
tj_text-0.10.0.dist-info/RECORD
