Metadata-Version: 2.3
Name: tj-text
Version: 0.10.0
Summary: Tj text utils
Author-email: Tj <tinkoffjournal@tjournal.tech>
Requires-Python: >=3.6
Classifier: Intended Audience :: Information Technology
Classifier: Intended Audience :: System Administrators
Classifier: Intended Audience :: Developers
Classifier: Operating System :: OS Independent
Classifier: Programming Language :: Python
Classifier: Programming Language :: Python :: 3
Classifier: Programming Language :: Python :: 3 :: Only
Classifier: Programming Language :: Python :: 3.6
Classifier: Programming Language :: Python :: 3.7
Classifier: Programming Language :: Python :: 3.8
Classifier: Programming Language :: Python :: 3.9
Classifier: Programming Language :: Python :: 3.10
Classifier: Programming Language :: Python :: 3.11
Classifier: Programming Language :: Python :: 3.12
Classifier: Topic :: Software Development :: Libraries :: Python Modules
Classifier: Topic :: Software Development :: Libraries
Classifier: Topic :: Software Development
Classifier: License :: OSI Approved :: MIT License
Requires-Dist: ipython ; extra == "dev"
Requires-Dist: black ; extra == "test"
Requires-Dist: isort ; extra == "test"
Requires-Dist: flake8 ; extra == "test"
Requires-Dist: pytest >=6.0.0 ; extra == "test"
Provides-Extra: dev
Provides-Extra: test
